langchain_scrapegraph/__init__.py
langchain_scrapegraph/tools/__init__.py
langchain_scrapegraph/tools/agentic_scraper.py
langchain_scrapegraph/tools/credits.py
langchain_scrapegraph/tools/markdownify.py
langchain_scrapegraph/tools/scheduled_jobs.py
langchain_scrapegraph/tools/scrape.py
langchain_scrapegraph/tools/searchscraper.py
langchain_scrapegraph/tools/smartcrawler.py
langchain_scrapegraph/tools/smartscraper.py
langchain_scrapegraph-1.6.0.dist-info/LICENSE
langchain_scrapegraph-1.6.0.dist-info/METADATA
langchain_scrapegraph-1.6.0.dist-info/WHEEL
langchain_scrapegraph-1.6.0.dist-info/RECORD
