Metadata-Version: 2.3
Name: langchain-scrapegraph
Version: 1.6.0
Summary: Library for extracting structured data from websites using ScrapeGraphAI
License: MIT
Keywords: scrapegraph,ai,artificial intelligence,gpt,machine learning,natural language processing,nlp,openai,graph,llm,langchain,scrape,scrape graph
Author: Marco Perini
Author-email: marco.perini@scrapegraphai.com
Requires-Python: >=3.10,<4.0
Classifier: Intended Audience :: Developers
Classifier: License :: OSI Approved :: MIT License
Classifier: Operating System :: OS Independent
Classifier: Programming Language :: Python :: 3
Classifier: Programming Language :: Python :: 3.10
Classifier: Programming Language :: Python :: 3.11
Classifier: Programming Language :: Python :: 3.12
Classifier: Programming Language :: Python :: 3.13
Classifier: Topic :: Software Development :: Libraries :: Python Modules
Requires-Dist: langchain-core (>=0.3.21,<0.4.0)
Requires-Dist: scrapegraph-py (==1.12.2)
Project-URL: Documentation, https://scrapegraphai.com/docs
Project-URL: Homepage, https://scrapegraphai.com/
Project-URL: Repository, https://github.com/scrapegraphai/langchain-scrapegraph
